.gitattributes
.gitignore
LICENSE
MANIFEST.in
README.md
setup.py
.ipynb_checkpoints/funnel_store_in_reports_index_example-checkpoint.ipynb
customeranalytics/.DS_Store
customeranalytics/__init__.py
customeranalytics/configs.py
customeranalytics/ea_and_ml_works.ipynb
customeranalytics/ml_processes_to_report_index.ipynb
customeranalytics/utils.py
customeranalytics.egg-info/PKG-INFO
customeranalytics.egg-info/SOURCES.txt
customeranalytics.egg-info/dependency_links.txt
customeranalytics.egg-info/requires.txt
customeranalytics.egg-info/top_level.txt
customeranalytics/.idea/.gitignore
customeranalytics/.idea/customeranalytics.iml
customeranalytics/.idea/misc.xml
customeranalytics/.idea/modules.xml
customeranalytics/.idea/vcs.xml
customeranalytics/.idea/workspace.xml
customeranalytics/.idea/inspectionProfiles/Project_Default.xml
customeranalytics/.idea/inspectionProfiles/profiles_settings.xml
customeranalytics/.ipynb_checkpoints/ea_and_ml_works-checkpoint.ipynb
customeranalytics/.ipynb_checkpoints/ml_processes_to_report_index-checkpoint.ipynb
customeranalytics/__pycache__/__init__.cpython-39.pyc
customeranalytics/__pycache__/configs.cpython-38.pyc
customeranalytics/__pycache__/configs.cpython-39.pyc
customeranalytics/__pycache__/utils.cpython-38.pyc
customeranalytics/__pycache__/utils.cpython-39.pyc
customeranalytics/data_storage_configurations/__init__.py
customeranalytics/data_storage_configurations/data_access.py
customeranalytics/data_storage_configurations/data_works_pipeline.py
customeranalytics/data_storage_configurations/es_create_index.py
customeranalytics/data_storage_configurations/logger.py
customeranalytics/data_storage_configurations/logs.log
customeranalytics/data_storage_configurations/query_es.py
customeranalytics/data_storage_configurations/reports.py
customeranalytics/data_storage_configurations/schedule_data_integration.py
customeranalytics/data_storage_configurations/__pycache__/__init__.cpython-38.pyc
customeranalytics/data_storage_configurations/__pycache__/__init__.cpython-39.pyc
customeranalytics/data_storage_configurations/__pycache__/data_access.cpython-39.pyc
