Metadata-Version: 2.1
Name: customeranalytics
Version: 0.0.2
Summary: 
Home-page: https://github.com/caglanakpinar/customer_analytics
Author: Caglan Akpinar
Author-email: cakpinar23@gmail.com
License: UNKNOWN
Keywords: Funnels,Cohorts,A/B Tests,e-commerce,CLV Prediction,Product Analytics,Churn,Anomaly Detection,Customer Segmentation,RFM,Statistics,Customer Analytics
Platform: UNKNOWN
Classifier: Programming Language :: Python :: 3
Classifier: License :: OSI Approved :: MIT License
Classifier: Operating System :: OS Independent
Requires-Python: >=3
